{"namedChunkGroups":{"polyfill":{"name":"polyfill","assets":[{"name":"webpack-runtime-e0a2b628b7bd402c7b55.js","size":3832},{"name":"polyfill-16cd3ae3bc737259f086.js","size":82631}],"filteredAssets":0,"assetsSize":86463,"filteredAuxiliaryAssets":2,"auxiliaryAssetsSize":216859},"app":{"name":"app","assets":[{"name":"webpack-runtime-e0a2b628b7bd402c7b55.js","size":3832},{"name":"framework-cb53c9c362859ae9bfa5.js","size":128959},{"name":"styles.4d371576f0919d60924b.css","size":5493},{"name":"app-51cdb8d6a1d5a7055a1d.js","size":66104}],"filteredAssets":0,"assetsSize":204388,"filteredAuxiliaryAssets":3,"auxiliaryAssetsSize":642754},"component---src-pages-404-tsx":{"name":"component---src-pages-404-tsx","assets":[{"name":"component---src-pages-404-tsx-73007e26bf84c670ecbb.js","size":314}],"filteredAssets":0,"assetsSize":314,"filteredAuxiliaryAssets":1,"auxiliaryAssetsSize":495},"component---src-pages-index-tsx":{"name":"component---src-pages-index-tsx","assets":[{"name":"1bfc9850-6efd8402f4353f41d329.js","size":2193},{"name":"component---src-pages-index-tsx-27142b4225691c82a915.js","size":20803}],"filteredAssets":0,"assetsSize":22996,"filteredAuxiliaryAssets":2,"auxiliaryAssetsSize":1543670}},"assetsByChunkName":{"polyfill":["webpack-runtime-e0a2b628b7bd402c7b55.js","polyfill-16cd3ae3bc737259f086.js"],"app":["webpack-runtime-e0a2b628b7bd402c7b55.js","framework-cb53c9c362859ae9bfa5.js","styles.4d371576f0919d60924b.css","app-51cdb8d6a1d5a7055a1d.js"],"component---src-pages-404-tsx":["component---src-pages-404-tsx-73007e26bf84c670ecbb.js"],"component---src-pages-index-tsx":["1bfc9850-6efd8402f4353f41d329.js","component---src-pages-index-tsx-27142b4225691c82a915.js"]},"childAssetsByChunkName":{}}